{
    "links": {
        "68c5507a2c044": {
            "date": "2025-09-13",
            "id": "68c5507a2c044",
            "name": "25 Spins",
            "game": "Coin Master",
            "type": "spins",
            "number": 25,
            "url": "https:\/\/rewards.coinmaster.com\/rewards\/rewards.html?c=pe_EMAILFKqZEy_20250910",
            "views": 0,
            "time": 1757761658
        },
        "68c52933c22fd": {
            "date": "2025-09-13",
            "id": "68c52933c22fd",
            "name": "50 Spins",
            "game": "Coin Master",
            "type": "spins",
            "number": 50,
            "url": "https:\/\/rewards.coinmaster.com\/rewards\/rewards.html?c=pe_FCBdaPiEw_20250913",
            "views": 0,
            "time": 1757751603
        },
        "68c4d983d42b5": {
            "date": "2025-09-13",
            "id": "68c4d983d42b5",
            "name": "50 Spins",
            "game": "Coin Master",
            "type": "spins",
            "number": 50,
            "url": "https:\/\/rewards.coinmaster.com\/rewards\/rewards.html?c=pe_HELPETGniP_20250913",
            "views": 0,
            "time": 1757731203
        },
        "68c4564457547": {
            "date": "2025-09-12",
            "id": "68c4564457547",
            "name": "50 Spins",
            "game": "Coin Master",
            "type": "spins",
            "number": 50,
            "url": "https:\/\/rewards.coinmaster.com\/rewards\/rewards.html?c=pe_FCBbbOUUd_20250912",
            "views": 0,
            "time": 1757697604
        },
        "68c401e330347": {
            "date": "2025-09-12",
            "id": "68c401e330347",
            "name": "25 Spins",
            "game": "Coin Master",
            "type": "spins",
            "number": 25,
            "url": "https:\/\/rewards.coinmaster.com\/rewards\/rewards.html?c=pe_EMAILNslZTU_20250910",
            "views": 0,
            "time": 1757676004
        },
        "68c401e330325": {
            "date": "2025-09-12",
            "id": "68c401e330325",
            "name": "50 Spins",
            "game": "Coin Master",
            "type": "spins",
            "number": 50,
            "url": "https:\/\/rewards.coinmaster.com\/rewards\/rewards.html?c=pe_FCBcVdewr_20250912",
            "views": 0,
            "time": 1757676003
        },
        "68c3f886014b2": {
            "date": "2025-09-12",
            "id": "68c3f886014b2",
            "name": "50 Spins",
            "game": "Coin Master",
            "type": "spins",
            "number": 50,
            "url": "https:\/\/rewards.coinmaster.com\/rewards\/rewards.html?c=pe_INSJirlXK_20250912",
            "views": 0,
            "time": 1757673606
        },
        "68c3dc636b394": {
            "date": "2025-09-12",
            "id": "68c3dc636b394",
            "name": "50 Spins",
            "game": "Coin Master",
            "type": "spins",
            "number": 50,
            "url": "https:\/\/rewards.coinmaster.com\/rewards\/rewards.html?c=pe_TWIGwWUvE_20250912",
            "views": 0,
            "time": 1757666403
        },
        "68c37093c7be3": {
            "date": "2025-09-12",
            "id": "68c37093c7be3",
            "name": "50 Spins",
            "game": "Coin Master",
            "type": "spins",
            "number": 50,
            "url": "https:\/\/rewards.coinmaster.com\/rewards\/rewards.html?c=pe_HELPKTRjZm_20250912",
            "views": 0,
            "time": 1757638803
        },
        "68c2d029e057d": {
            "date": "2025-09-11",
            "id": "68c2d029e057d",
            "name": "50 Spins",
            "game": "Coin Master",
            "type": "spins",
            "number": 50,
            "url": "https:\/\/rewards.coinmaster.com\/rewards\/rewards.html?c=pe_FCBeyhvoV_20250911",
            "views": 0,
            "time": 1757597737
        },
        "68c2be73cfa66": {
            "date": "2025-09-11",
            "id": "68c2be73cfa66",
            "name": "60 Spins",
            "game": "Coin Master",
            "type": "spins",
            "number": 60,
            "url": "https:\/\/rewards.coinmaster.com\/rewards\/rewards.html?c=pe_RICHNbMGQZ_20250816",
            "views": 0,
            "time": 1757593203
        },
        "68c2b513c5aca": {
            "date": "2025-09-11",
            "id": "68c2b513c5aca",
            "name": "50 Spins",
            "game": "Coin Master",
            "type": "spins",
            "number": 50,
            "url": "https:\/\/rewards.coinmaster.com\/rewards\/rewards.html?c=pe_LINEqpwmKa_20250911",
            "views": 0,
            "time": 1757590803
        },
        "68c2ad7cced26": {
            "date": "2025-09-11",
            "id": "68c2ad7cced26",
            "name": "25 Spins",
            "game": "Coin Master",
            "type": "spins",
            "number": 25,
            "url": "https:\/\/rewards.coinmaster.com\/rewards\/rewards.html?c=pe_EMAILawLBEO_20250909",
            "views": 0,
            "time": 1757588860
        },
        "68c28f93e9e8d": {
            "date": "2025-09-11",
            "id": "68c28f93e9e8d",
            "name": "50 Spins",
            "game": "Coin Master",
            "type": "spins",
            "number": 50,
            "url": "https:\/\/rewards.coinmaster.com\/rewards\/rewards.html?c=pe_INSdyCDqG_20250911",
            "views": 0,
            "time": 1757581203
        },
        "68c28ae35748c": {
            "date": "2025-09-11",
            "id": "68c28ae35748c",
            "name": "50 Spins",
            "game": "Coin Master",
            "type": "spins",
            "number": 50,
            "url": "https:\/\/rewards.coinmaster.com\/rewards\/rewards.html?c=pe_TWIehnEym_20250911",
            "views": 0,
            "time": 1757580003
        },
        "68c286334e806": {
            "date": "2025-09-11",
            "id": "68c286334e806",
            "name": "50 Spins",
            "game": "Coin Master",
            "type": "spins",
            "number": 50,
            "url": "https:\/\/rewards.coinmaster.com\/rewards\/rewards.html?c=pe_FCBkBZLUv_20250911",
            "views": 0,
            "time": 1757578803
        },
        "68c23b3388052": {
            "date": "2025-09-11",
            "id": "68c23b3388052",
            "name": "50 Spins",
            "game": "Coin Master",
            "type": "spins",
            "number": 50,
            "url": "https:\/\/rewards.coinmaster.com\/rewards\/rewards.html?c=pe_HELPdyzTSR_20250911",
            "views": 0,
            "time": 1757559603
        },
        "68c1b343d6160": {
            "date": "2025-09-10",
            "id": "68c1b343d6160",
            "name": "50 Spins",
            "game": "Coin Master",
            "type": "spins",
            "number": 50,
            "url": "https:\/\/rewards.coinmaster.com\/rewards\/rewards.html?c=pe_FCBBBsJCC_20250910",
            "views": 0,
            "time": 1757524803
        },
        "68c17b03400f9": {
            "date": "2025-09-10",
            "id": "68c17b03400f9",
            "name": "50 Spins",
            "game": "Coin Master",
            "type": "spins",
            "number": 50,
            "url": "https:\/\/rewards.coinmaster.com\/rewards\/rewards.html?c=pe_LINESBLzPj_20250910",
            "views": 0,
            "time": 1757510403
        },
        "68c15c04031dd": {
            "date": "2025-09-10",
            "id": "68c15c04031dd",
            "name": "25 Spins",
            "game": "Coin Master",
            "type": "spins",
            "number": 25,
            "url": "https:\/\/rewards.coinmaster.com\/rewards\/rewards.html?c=pe_EMAILHcEtjE_20250908",
            "views": 0,
            "time": 1757502468
        },
        "68c1477800d32": {
            "date": "2025-09-10",
            "id": "68c1477800d32",
            "name": "50 Spins",
            "game": "Coin Master",
            "type": "spins",
            "number": 50,
            "url": "https:\/\/rewards.coinmaster.com\/rewards\/rewards.html?c=pe_INSmLdOLb_20250910",
            "views": 0,
            "time": 1757497208
        },
        "68c13004d37fb": {
            "date": "2025-09-10",
            "id": "68c13004d37fb",
            "name": "50 Spins",
            "game": "Coin Master",
            "type": "spins",
            "number": 50,
            "url": "https:\/\/rewards.coinmaster.com\/rewards\/rewards.html?c=pe_FCBauOTSO_20250910",
            "views": 0,
            "time": 1757491204
        },
        "68c0cd93e6f57": {
            "date": "2025-09-10",
            "id": "68c0cd93e6f57",
            "name": "50 Spins",
            "game": "Coin Master",
            "type": "spins",
            "number": 50,
            "url": "https:\/\/rewards.coinmaster.com\/rewards\/rewards.html?c=pe_HELPuauZFP_20250910",
            "views": 0,
            "time": 1757466003
        },
        "68c061c44c0c7": {
            "date": "2025-09-09",
            "id": "68c061c44c0c7",
            "name": "50 Spins",
            "game": "Coin Master",
            "type": "spins",
            "number": 50,
            "url": "https:\/\/rewards.coinmaster.com\/rewards\/rewards.html?c=pe_FCBagvTiy_20250909",
            "views": 0,
            "time": 1757438404
        }
    }
}