{
    "links": {
        "699e44e66f8ea": {
            "date": "2026-02-25",
            "id": "699e44e66f8ea",
            "name": "50 Spins",
            "game": "Coin Master",
            "type": "spins",
            "number": 50,
            "url": "https:\/\/rewards.coinmaster.com\/rewards\/rewards.html?c=pe_HELPyFdWQO_20260225",
            "views": 0,
            "time": 1771980006
        },
        "699e0345abd1e": {
            "date": "2026-02-24",
            "id": "699e0345abd1e",
            "name": "50 Spins",
            "game": "Coin Master",
            "type": "spins",
            "number": 50,
            "url": "https:\/\/rewards.coinmaster.com\/rewards\/rewards.html?c=pe_FCBwLyyFI_20260224",
            "views": 0,
            "time": 1771963205
        },
        "699d8e14d636d": {
            "date": "2026-02-24",
            "id": "699d8e14d636d",
            "name": "25 Spins",
            "game": "Coin Master",
            "type": "spins",
            "number": 25,
            "url": "https:\/\/rewards.coinmaster.com\/rewards\/rewards.html?c=pe_EMAILkNMhZV_20260223",
            "views": 0,
            "time": 1771933204
        },
        "699d80049af74": {
            "date": "2026-02-24",
            "id": "699d80049af74",
            "name": "50 Spins",
            "game": "Coin Master",
            "type": "spins",
            "number": 50,
            "url": "https:\/\/rewards.coinmaster.com\/rewards\/rewards.html?c=pe_FCBXpaWUB_20260224",
            "views": 0,
            "time": 1771929605
        },
        "699d80049af4a": {
            "date": "2026-02-24",
            "id": "699d80049af4a",
            "name": "50 Spins",
            "game": "Coin Master",
            "type": "spins",
            "number": 50,
            "url": "https:\/\/rewards.coinmaster.com\/rewards\/rewards.html?c=pe_FCBMuWBgd_20260223",
            "views": 0,
            "time": 1771929604
        },
        "699d7b5682b00": {
            "date": "2026-02-24",
            "id": "699d7b5682b00",
            "name": "50 Spins",
            "game": "Coin Master",
            "type": "spins",
            "number": 50,
            "url": "https:\/\/rewards.coinmaster.com\/rewards\/rewards.html?c=pe_INSdvusFC_20260224",
            "views": 0,
            "time": 1771928406
        },
        "699d43138d5fb": {
            "date": "2026-02-24",
            "id": "699d43138d5fb",
            "name": "50 Spins",
            "game": "Coin Master",
            "type": "spins",
            "number": 50,
            "url": "https:\/\/rewards.coinmaster.com\/rewards\/rewards.html?c=pe_FCBsADxtw_20260223",
            "views": 0,
            "time": 1771914003
        },
        "699cfcc42949a": {
            "date": "2026-02-24",
            "id": "699cfcc42949a",
            "name": "50 Spins",
            "game": "Coin Master",
            "type": "spins",
            "number": 50,
            "url": "https:\/\/rewards.coinmaster.com\/rewards\/rewards.html?c=pe_HELPeycRnq_20260224",
            "views": 0,
            "time": 1771896004
        },
        "699c9a552f555": {
            "date": "2026-02-23",
            "id": "699c9a552f555",
            "name": "50 Spins",
            "game": "Coin Master",
            "type": "spins",
            "number": 50,
            "url": "https:\/\/rewards.coinmaster.com\/rewards\/rewards.html?c=pe_FCBZoClmZ_20260223",
            "views": 0,
            "time": 1771870805
        },
        "699c66c57056f": {
            "date": "2026-02-23",
            "id": "699c66c57056f",
            "name": "50 Spins",
            "game": "Coin Master",
            "type": "spins",
            "number": 50,
            "url": "https:\/\/rewards.coinmaster.com\/rewards\/rewards.html?c=pe_CHATBrvircm_20260223",
            "views": 0,
            "time": 1771857605
        },
        "699c58b5cd217": {
            "date": "2026-02-23",
            "id": "699c58b5cd217",
            "name": "50 Spins",
            "game": "Coin Master",
            "type": "spins",
            "number": 50,
            "url": "https:\/\/rewards.coinmaster.com\/rewards\/rewards.html?c=pe_LINEGNHNdx_20260223",
            "views": 0,
            "time": 1771854005
        },
        "699c54061e16f": {
            "date": "2026-02-23",
            "id": "699c54061e16f",
            "name": "50 Spins",
            "game": "Coin Master",
            "type": "spins",
            "number": 50,
            "url": "https:\/\/rewards.coinmaster.com\/rewards\/rewards.html?c=pe_TWIjqRavk_20260223",
            "views": 0,
            "time": 1771852807
        },
        "699c54061e13d": {
            "date": "2026-02-23",
            "id": "699c54061e13d",
            "name": "50 Spins",
            "game": "Coin Master",
            "type": "spins",
            "number": 50,
            "url": "https:\/\/rewards.coinmaster.com\/rewards\/rewards.html?c=pe_FCBifpsMC_20260223",
            "views": 0,
            "time": 1771852806
        },
        "699c3c9682b89": {
            "date": "2026-02-23",
            "id": "699c3c9682b89",
            "name": "100 Spins",
            "game": "Coin Master",
            "type": "spins",
            "number": 100,
            "url": "https:\/\/rewards.coinmaster.com\/rewards\/rewards.html?c=pe_RICHXZLtYZ_20260126",
            "views": 0,
            "time": 1771846806
        },
        "699c37e61619d": {
            "date": "2026-02-23",
            "id": "699c37e61619d",
            "name": "25 Spins",
            "game": "Coin Master",
            "type": "spins",
            "number": 25,
            "url": "https:\/\/rewards.coinmaster.com\/rewards\/rewards.html?c=pe_EMAILrIMYLC_20260222",
            "views": 0,
            "time": 1771845606
        },
        "699c2528b77d9": {
            "date": "2026-02-23",
            "id": "699c2528b77d9",
            "name": "50 Spins",
            "game": "Coin Master",
            "type": "spins",
            "number": 50,
            "url": "https:\/\/rewards.coinmaster.com\/rewards\/rewards.html?c=pe_INSUHGrHD_20260223",
            "views": 0,
            "time": 1771840808
        },
        "699ba1e4ea241": {
            "date": "2026-02-23",
            "id": "699ba1e4ea241",
            "name": "50 Spins",
            "game": "Coin Master",
            "type": "spins",
            "number": 50,
            "url": "https:\/\/rewards.coinmaster.com\/rewards\/rewards.html?c=pe_HELPxloQBh_20260223",
            "views": 0,
            "time": 1771807204
        },
        "699b4d84427c6": {
            "date": "2026-02-22",
            "id": "699b4d84427c6",
            "name": "50 Spins",
            "game": "Coin Master",
            "type": "spins",
            "number": 50,
            "url": "https:\/\/rewards.coinmaster.com\/rewards\/rewards.html?c=pe_FCBUYxfue_20260222",
            "views": 0,
            "time": 1771785604
        },
        "699aefc49ff0b": {
            "date": "2026-02-22",
            "id": "699aefc49ff0b",
            "name": "50 Spins",
            "game": "Coin Master",
            "type": "spins",
            "number": 50,
            "url": "https:\/\/rewards.coinmaster.com\/rewards\/rewards.html?c=pe_INSEWAnfk_20260222",
            "views": 0,
            "time": 1771761604
        },
        "699aeb1453925": {
            "date": "2026-02-22",
            "id": "699aeb1453925",
            "name": "50 Spins",
            "game": "Coin Master",
            "type": "spins",
            "number": 50,
            "url": "https:\/\/rewards.coinmaster.com\/rewards\/rewards.html?c=pe_LINEfJGGyv_20260222",
            "views": 0,
            "time": 1771760404
        },
        "699aca44112af": {
            "date": "2026-02-22",
            "id": "699aca44112af",
            "name": "50 Spins",
            "game": "Coin Master",
            "type": "spins",
            "number": 50,
            "url": "https:\/\/rewards.coinmaster.com\/rewards\/rewards.html?c=pe_FCBgrHfXk_20260222",
            "views": 0,
            "time": 1771752004
        },
        "699a9b6967aed": {
            "date": "2026-02-22",
            "id": "699a9b6967aed",
            "name": "50 Spins",
            "game": "Coin Master",
            "type": "spins",
            "number": 50,
            "url": "https:\/\/rewards.coinmaster.com\/rewards\/rewards.html?c=pe_TWIQMtwai_20260222",
            "views": 0,
            "time": 1771740009
        },
        "699a7136c12cc": {
            "date": "2026-02-22",
            "id": "699a7136c12cc",
            "name": "50 Spins",
            "game": "Coin Master",
            "type": "spins",
            "number": 50,
            "url": "https:\/\/rewards.coinmaster.com\/rewards\/rewards.html?c=pe_LINEfqZJaD_20260221",
            "views": 0,
            "time": 1771729206
        },
        "699a50645d794": {
            "date": "2026-02-22",
            "id": "699a50645d794",
            "name": "50 Spins",
            "game": "Coin Master",
            "type": "spins",
            "number": 50,
            "url": "https:\/\/rewards.coinmaster.com\/rewards\/rewards.html?c=pe_HELPIwtpyR_20260222",
            "views": 0,
            "time": 1771720804
        },
        "6999bf1515e2b": {
            "date": "2026-02-21",
            "id": "6999bf1515e2b",
            "name": "50 Spins",
            "game": "Coin Master",
            "type": "spins",
            "number": 50,
            "url": "https:\/\/rewards.coinmaster.com\/rewards\/rewards.html?c=pe_TWIHrUMjB_20260221",
            "views": 0,
            "time": 1771683605
        },
        "6999a7a48a428": {
            "date": "2026-02-21",
            "id": "6999a7a48a428",
            "name": "50 Spins",
            "game": "Coin Master",
            "type": "spins",
            "number": 50,
            "url": "https:\/\/rewards.coinmaster.com\/rewards\/rewards.html?c=pe_FCBKUnVik_20260221",
            "views": 0,
            "time": 1771677604
        },
        "6999a2f49c3e8": {
            "date": "2026-02-21",
            "id": "6999a2f49c3e8",
            "name": "25 Spins",
            "game": "Coin Master",
            "type": "spins",
            "number": 25,
            "url": "https:\/\/rewards.coinmaster.com\/rewards\/rewards.html?c=pe_EMAILbiqxoq_20260220",
            "views": 0,
            "time": 1771676404
        },
        "69998b843fbd3": {
            "date": "2026-02-21",
            "id": "69998b843fbd3",
            "name": "50 Spins",
            "game": "Coin Master",
            "type": "spins",
            "number": 50,
            "url": "https:\/\/rewards.coinmaster.com\/rewards\/rewards.html?c=pe_INSTZcwhn_20260221",
            "views": 0,
            "time": 1771670404
        }
    }
}