{
    "links": {
        "6a1d89927ebde": {
            "id": "6a1d89927ebde",
            "date": "2026-06-01",
            "name": "Match Masters Bonus",
            "game": "Match Masters",
            "type": "mat masters",
            "number": 0,
            "url": "https://launch.matchmasters.com/l/p/SPi6b4chxGk",
            "views": 0,
            "time": 1780320659
        },
        "6a1d89926b700": {
            "id": "6a1d89926b700",
            "date": "2026-06-01",
            "name": "Match Masters Bonus",
            "game": "Match Masters",
            "type": "mat masters",
            "number": 0,
            "url": "https://launch.matchmasters.com/l/p/KSB1lE6g0SU",
            "views": 0,
            "time": 1780320658
        },
        "6a1d8982bdfbf": {
            "id": "6a1d8982bdfbf",
            "date": "2026-06-01",
            "name": "Travel Town Bonus",
            "game": "Travel Town",
            "type": "energy",
            "number": 25,
            "url": "https://api.traveltowngame.net/public/rewardLinks/getLink/v0N4l1Ln_FCB",
            "views": 0,
            "time": 1780320644
        },
        "6a1d8982a83ff": {
            "id": "6a1d8982a83ff",
            "date": "2026-06-01",
            "name": "Travel Town Bonus",
            "game": "Travel Town",
            "type": "energy",
            "number": 10,
            "url": "https://api.traveltowngame.net/public/rewardLinks/getLink/y1G6DWAc_TWI",
            "views": 0,
            "time": 1780320643
        },
        "6a1d89828edf7": {
            "id": "6a1d89828edf7",
            "date": "2026-06-01",
            "name": "Travel Town Bonus",
            "game": "Travel Town",
            "type": "energy",
            "number": 15,
            "url": "https://api.traveltowngame.net/public/rewardLinks/getLink/mxLQtmAW_INS",
            "views": 0,
            "time": 1780320642
        },
        "6a1d6d4c04efe": {
            "date": "2026-06-01",
            "id": "6a1d6d4c04efe",
            "name": "Coin Tales Bonus",
            "game": "Coin Tales",
            "type": "other",
            "number": 50,
            "url": "https://cutt.ly/ft1ZaYaB",
            "views": 0,
            "time": 1780313420
        },
        "6a1d6d4be4e6d": {
            "date": "2026-06-01",
            "id": "6a1d6d4be4e6d",
            "name": "Coin Dragon Bonus",
            "game": "Coin Dragon",
            "type": "other",
            "number": 20,
            "url": "https://www.game-ease.com/reward.html?dc=s65f0mk6",
            "views": 0,
            "time": 1780313419
        },
        "6a1d5170d93ca": {
            "id": "6a1d5170d93ca",
            "date": "2026-06-01",
            "name": "Match Masters Bonus",
            "game": "Match Masters",
            "type": "mat masters",
            "number": 0,
            "url": "https://launch.matchmasters.com/l/p/TiJ62ZXzqpI",
            "views": 0,
            "time": 1780306291
        },
        "6a1d5170be458": {
            "id": "6a1d5170be458",
            "date": "2026-06-01",
            "name": "Match Masters Bonus",
            "game": "Match Masters",
            "type": "mat masters",
            "number": 0,
            "url": "https://launch.matchmasters.com/l/p/8b0vizmqirs",
            "views": 0,
            "time": 1780306290
        },
        "6a1d5170aaca6": {
            "id": "6a1d5170aaca6",
            "date": "2026-06-01",
            "name": "Match Masters Bonus",
            "game": "Match Masters",
            "type": "mat masters",
            "number": 0,
            "url": "https://launch.matchmasters.com/l/p/LHWpjdqj5eg",
            "views": 0,
            "time": 1780306289
        },
        "6a1d5170948c2": {
            "id": "6a1d5170948c2",
            "date": "2026-06-01",
            "name": "Match Masters Bonus",
            "game": "Match Masters",
            "type": "mat masters",
            "number": 0,
            "url": "https://launch.matchmasters.com/l/p/8XlfT6N8FQQ",
            "views": 0,
            "time": 1780306288
        },
        "6a1d516deb722": {
            "id": "6a1d516deb722",
            "date": "2026-06-01",
            "name": "Dice Dreams Bonus",
            "game": "Dice Dreams",
            "type": "dice",
            "number": 50,
            "url": "https://rewards.dicedreams.com/?handler=reward&link=CommunityPost_310526cxz",
            "views": 0,
            "time": 1780306287
        },
        "6a1d516dd6617": {
            "id": "6a1d516dd6617",
            "date": "2026-06-01",
            "name": "Dice Dreams Bonus",
            "game": "Dice Dreams",
            "type": "dice",
            "number": 50,
            "url": "https://rewards.dicedreams.com/?handler=reward&link=CommunityWhatsapp_2_310526baa",
            "views": 0,
            "time": 1780306286
        },
        "6a1d516daeae8": {
            "id": "6a1d516daeae8",
            "date": "2026-06-01",
            "name": "Dice Dreams Bonus",
            "game": "Dice Dreams",
            "type": "dice",
            "number": 50,
            "url": "https://rewards.dicedreams.com/?handler=reward&link=CommunityStory_310526bbb",
            "views": 0,
            "time": 1780306285
        },
        "6a1d514e18dae": {
            "id": "6a1d514e18dae",
            "date": "2026-06-01",
            "name": "Travel Town Bonus",
            "game": "Travel Town",
            "type": "energy",
            "number": 10,
            "url": "https://api.traveltowngame.net/public/rewardLinks/getLink/KBKL97wH_TRADING",
            "views": 0,
            "time": 1780306254
        },
        "6a1c95cd23838": {
            "id": "6a1c95cd23838",
            "date": "2026-05-31",
            "name": "Travel Town Bonus",
            "game": "Travel Town",
            "type": "energy",
            "number": 20,
            "url": "https://api.traveltowngame.net/public/rewardLinks/getLink/E5YLnKQC_WA",
            "views": 0,
            "time": 1780258253
        },
        "6a1c5dc0bffdc": {
            "id": "6a1c5dc0bffdc",
            "date": "2026-05-31",
            "name": "Match Masters Bonus",
            "game": "Match Masters",
            "type": "mat masters",
            "number": 0,
            "url": "https://launch.matchmasters.com/l/p/7byTZj_12jM",
            "views": 0,
            "time": 1780243904
        },
        "6a1c5d86ca044": {
            "date": "2026-05-31",
            "id": "6a1c5d86ca044",
            "name": "Family Island Bonus",
            "game": "Family Island",
            "type": "energy",
            "number": 0,
            "url": "https://thefamilyisland.com/4udfFOv",
            "views": 0,
            "time": 1780243846
        },
        "6a1c383c13d02": {
            "id": "6a1c383c13d02",
            "date": "2026-05-31",
            "name": "Match Masters Bonus",
            "game": "Match Masters",
            "type": "mat masters",
            "number": 0,
            "url": "https://launch.matchmasters.com/l/p/Yfd2fMgRRSM",
            "views": 0,
            "time": 1780234300
        },
        "6a1c382885a87": {
            "id": "6a1c382885a87",
            "date": "2026-05-31",
            "name": "Match Masters Bonus",
            "game": "Match Masters",
            "type": "mat masters",
            "number": 0,
            "url": "https://launch.matchmasters.com/l/p/hICYPSQpuWw",
            "views": 0,
            "time": 1780234283
        },
        "6a1c382862de5": {
            "id": "6a1c382862de5",
            "date": "2026-05-31",
            "name": "Match Masters Bonus",
            "game": "Match Masters",
            "type": "mat masters",
            "number": 0,
            "url": "https://launch.matchmasters.com/l/p/wvANiJPglvw",
            "views": 0,
            "time": 1780234282
        },
        "6a1c38283ca90": {
            "id": "6a1c38283ca90",
            "date": "2026-05-31",
            "name": "Match Masters Bonus",
            "game": "Match Masters",
            "type": "mat masters",
            "number": 0,
            "url": "https://launch.matchmasters.com/l/p/irjxkPuVqdE",
            "views": 0,
            "time": 1780234281
        },
        "6a1c38281e397": {
            "id": "6a1c38281e397",
            "date": "2026-05-31",
            "name": "Match Masters Bonus",
            "game": "Match Masters",
            "type": "mat masters",
            "number": 0,
            "url": "https://launch.matchmasters.com/l/p/6FRIOZazuzc",
            "views": 0,
            "time": 1780234280
        },
        "6a1c38252d576": {
            "id": "6a1c38252d576",
            "date": "2026-05-31",
            "name": "Dice Dreams Bonus",
            "game": "Dice Dreams",
            "type": "dice",
            "number": 50,
            "url": "https://rewards.dicedreams.com/?handler=reward&link=CommunityPost_300526law",
            "views": 0,
            "time": 1780234278
        },
        "6a1c38250e303": {
            "id": "6a1c38250e303",
            "date": "2026-05-31",
            "name": "Dice Dreams Bonus",
            "game": "Dice Dreams",
            "type": "dice",
            "number": 50,
            "url": "https://rewards.dicedreams.com/?handler=reward&link=CommunityStory_300526ccc",
            "views": 0,
            "time": 1780234277
        },
        "6a1c3800dc538": {
            "date": "2026-05-31",
            "id": "6a1c3800dc538",
            "name": "Coin Dragon Bonus",
            "game": "Coin Dragon",
            "type": "other",
            "number": 20,
            "url": "https://www.game-ease.com/reward.html?dc=bvn7yxb9",
            "views": 0,
            "time": 1780234240
        },
        "6a1c1bed6576d": {
            "id": "6a1c1bed6576d",
            "date": "2026-05-31",
            "name": "Travel Town Bonus",
            "game": "Travel Town",
            "type": "energy",
            "number": 25,
            "url": "https://api.traveltowngame.net/public/rewardLinks/getLink/kfRIJnio_FCB",
            "views": 0,
            "time": 1780227056
        },
        "6a1c1bed547a6": {
            "id": "6a1c1bed547a6",
            "date": "2026-05-31",
            "name": "Travel Town Bonus",
            "game": "Travel Town",
            "type": "energy",
            "number": 10,
            "url": "https://api.traveltowngame.net/public/rewardLinks/getLink/Qr4z9lnk_TWI",
            "views": 0,
            "time": 1780227055
        },
        "6a1c1bed43777": {
            "id": "6a1c1bed43777",
            "date": "2026-05-31",
            "name": "Travel Town Bonus",
            "game": "Travel Town",
            "type": "energy",
            "number": 15,
            "url": "https://api.traveltowngame.net/public/rewardLinks/getLink/9MIlPw0N_INS",
            "views": 0,
            "time": 1780227054
        },
        "6a1c1bed2fbbb": {
            "id": "6a1c1bed2fbbb",
            "date": "2026-05-31",
            "name": "Travel Town Bonus",
            "game": "Travel Town",
            "type": "energy",
            "number": 20,
            "url": "https://api.traveltowngame.net/public/rewardLinks/getLink/s29gWeqH_WA",
            "views": 0,
            "time": 1780227053
        },
        "6a1b44393bcd1": {
            "id": "6a1b44393bcd1",
            "date": "2026-05-30",
            "name": "Travel Town Bonus",
            "game": "Travel Town",
            "type": "energy",
            "number": 10,
            "url": "https://api.traveltowngame.net/public/rewardLinks/getLink/iIo7U8J9_TRADING",
            "views": 0,
            "time": 1780171833
        },
        "6a1b0c238f887": {
            "id": "6a1b0c238f887",
            "date": "2026-05-30",
            "name": "Travel Town Bonus",
            "game": "Travel Town",
            "type": "energy",
            "number": 25,
            "url": "https://api.traveltowngame.net/public/rewardLinks/getLink/Ujfi4T55_FCB",
            "views": 0,
            "time": 1780157478
        },
        "6a1b0c236b2e0": {
            "id": "6a1b0c236b2e0",
            "date": "2026-05-30",
            "name": "Travel Town Bonus",
            "game": "Travel Town",
            "type": "energy",
            "number": 25,
            "url": "https://api.traveltowngame.net/public/rewardLinks/getLink/sg23oFCo_INS",
            "views": 0,
            "time": 1780157477
        },
        "6a1b0c2347aca": {
            "id": "6a1b0c2347aca",
            "date": "2026-05-30",
            "name": "Travel Town Bonus",
            "game": "Travel Town",
            "type": "energy",
            "number": 10,
            "url": "https://api.traveltowngame.net/public/rewardLinks/getLink/zBRqIre3_TWI",
            "views": 0,
            "time": 1780157476
        },
        "6a1b0c232184b": {
            "id": "6a1b0c232184b",
            "date": "2026-05-30",
            "name": "Travel Town Bonus",
            "game": "Travel Town",
            "type": "energy",
            "number": 10,
            "url": "https://api.traveltowngame.net/public/rewardLinks/getLink/f6e0VOzZ_TRADING",
            "views": 0,
            "time": 1780157475
        },
        "6a1aca5669036": {
            "date": "2026-05-30",
            "id": "6a1aca5669036",
            "name": "Family Island Bonus",
            "game": "Family Island",
            "type": "energy",
            "number": 0,
            "url": "https://thefamilyisland.com/4a6LOPv",
            "views": 0,
            "time": 1780140634
        },
        "6a1aca5645304": {
            "date": "2026-05-30",
            "id": "6a1aca5645304",
            "name": "Family Island Bonus",
            "game": "Family Island",
            "type": "energy",
            "number": 0,
            "url": "https://familyisland.onelink.me/wjlA/5cf53k9e",
            "views": 0,
            "time": 1780140633
        },
        "6a1aca5620051": {
            "date": "2026-05-30",
            "id": "6a1aca5620051",
            "name": "Family Island Bonus",
            "game": "Family Island",
            "type": "energy",
            "number": 0,
            "url": "https://thefamilyisland.com/3OYKtmQ",
            "views": 0,
            "time": 1780140632
        },
        "6a1aca55b3bc1": {
            "date": "2026-05-30",
            "id": "6a1aca55b3bc1",
            "name": "Family Island Bonus",
            "game": "Family Island",
            "type": "energy",
            "number": 0,
            "url": "https://thefamilyisland.com/436y1Vj",
            "views": 0,
            "time": 1780140631
        },
        "6a1aca5595b15": {
            "date": "2026-05-30",
            "id": "6a1aca5595b15",
            "name": "Family Island Bonus",
            "game": "Family Island",
            "type": "energy",
            "number": 0,
            "url": "https://thefamilyisland.com/4dLZxfZ",
            "views": 0,
            "time": 1780140630
        },
        "6a1aca5564dd8": {
            "date": "2026-05-30",
            "id": "6a1aca5564dd8",
            "name": "Coin Dragon Bonus",
            "game": "Coin Dragon",
            "type": "other",
            "number": 20,
            "url": "https://www.game-ease.com/reward.html?dc=mghfr4q5",
            "views": 0,
            "time": 1780140629
        },
        "6a1aae3a144c9": {
            "id": "6a1aae3a144c9",
            "date": "2026-05-30",
            "name": "Travel Town Bonus",
            "game": "Travel Town",
            "type": "energy",
            "number": 20,
            "url": "https://api.traveltowngame.net/public/rewardLinks/getLink/WxGAGyWq_WA",
            "views": 0,
            "time": 1780133434
        }
    }
}